simplepy/__init__.py
simplepy/async_db.py
simplepy/chrome.py
simplepy/config.py
simplepy/credit_code.py
simplepy/db.py
simplepy/decorators.py
simplepy/faker_base.py
simplepy/fastDFS_client.py
simplepy/frida_base.py
simplepy/graph.py
simplepy/helpers.py
simplepy/html2pdf.py
simplepy/logger.py
simplepy/mail.py
simplepy/multi_download.py
simplepy/nfs_client.py
simplepy/numpy_utils.py
simplepy/pandas_utils.py
simplepy/plot.py
simplepy/proxy.py
simplepy/re_libs.py
simplepy/request.py
simplepy/resources.py
simplepy/secert.py
simplepy/smb_client.py
simplepy/snow_id.py
simplepy/spider.py
simplepy/tests.py
simplepy/utils.py
simplepy/web.py
simplepy/win32_api.py
simplepy-2.0.0.dist-info/METADATA
simplepy-2.0.0.dist-info/WHEEL
simplepy-2.0.0.dist-info/top_level.txt
simplepy-2.0.0.dist-info/RECORD
