Metadata-Version: 2.1
Name: simplepy
Version: 2.0.0
Summary: Python General Toolkit Collection
Home-page: https://github.com/fovegage/simplepy
Author: fovegage
Author-email: fovegage@gmail.com
License: UNKNOWN
Platform: UNKNOWN
Classifier: Programming Language :: Python :: 3
Classifier: License :: OSI Approved :: MIT License
Classifier: Operating System :: OS Independent
Requires-Dist: pysnowflake
Requires-Dist: setuptools-rust
Requires-Dist: scikit-build
Requires-Dist: cmake
Requires-Dist: opencv-python
Requires-Dist: PyCryptodome
Requires-Dist: pandas
Requires-Dist: pymongo
Requires-Dist: pymysql
Requires-Dist: redis
Requires-Dist: environs
Requires-Dist: lxml
Requires-Dist: selenium
Requires-Dist: requests
Requires-Dist: aiohttp
Requires-Dist: flask
Requires-Dist: loguru
Requires-Dist: frida
Requires-Dist: imap-tools
Requires-Dist: tenacity
Requires-Dist: matplotlib
Requires-Dist: jieba
Requires-Dist: sqlalchemy
Requires-Dist: pypac
Requires-Dist: simplejson
Requires-Dist: pyDes
Requires-Dist: paramiko
Requires-Dist: numpy
Requires-Dist: faker
Requires-Dist: BeautifulSoup4
Requires-Dist: pyvirtualdisplay
Requires-Dist: python-consul2
Requires-Dist: pysmb
Requires-Dist: py3Fdfs
Requires-Dist: oss2
